core/__init__.py
core/core.py
core/assistant/__init__.py
core/assistant/config.py
core/assistant/core_assistant.py
core/interface/__init__.py
core/interface/assistant_interface.py
cowgirl_ai_core-1.0.2.dist-info/LICENSE
cowgirl_ai_core-1.0.2.dist-info/METADATA
cowgirl_ai_core-1.0.2.dist-info/WHEEL
cowgirl_ai_core-1.0.2.dist-info/entry_points.txt
cowgirl_ai_core-1.0.2.dist-info/top_level.txt
cowgirl_ai_core-1.0.2.dist-info/RECORD
