Metadata-Version: 2.1
Name: cowgirl-ai-core
Version: 1.0.2
Summary: Cowgirl AI - Core Assistant
Home-page: https://github.com/Cowgirl-AI/core
Author: Tera Earlywine
Author-email: dev@teraearlywine.com
Requires-Python: >=3.10
License-File: LICENSE
